data/Dual-MindMap.empty.trt
data/Simple-Task-List.empty.trt
data/Simple-Task-List.trt
data/Single-MindMap.empty.trt
data/Tutorial.trt
data/treetime-logo.png
docs/abcde01.png
docs/abcde02.png
docs/linked-trees.png
docs/screenshot01.png
docs/screenshot02.png
docs/screenshot03.png
docs/screenshot04.png
treetime/__init__.py
treetime/__main__.py
treetime/compile-ui.py
treetime/item.py
treetime/mainwindow.py
treetime/test.py
treetime/tree.py
treetime/treetime.py
TreeTime-2023.1.dist-info/LICENSE.txt
TreeTime-2023.1.dist-info/METADATA
TreeTime-2023.1.dist-info/WHEEL
TreeTime-2023.1.dist-info/entry_points.txt
TreeTime-2023.1.dist-info/top_level.txt
TreeTime-2023.1.dist-info/RECORD
