Metadata-Version: 2.1
Name: TreeTime
Version: 2023.1
Summary: TreeTime is a to-do list manager, test report tool, project manager, family ancestry editor,mind-mapping tool, etc. Using TreeTime you can categorise and organise any data in tree structures.You can define several trees, each with a different structure, on the same data. You can use functions(sums, ratios and means) recursively up the branches of a tree.
Home-page: https://github.com/jkanev/treetime
Author: Jacob Kanev
Author-email: jkanev@zoho.com
License-File: LICENSE.txt
